_pybinding.cpython-312-darwin.so
pybinding_dev-1.0.6.dist-info/RECORD
pybinding_dev-1.0.6.dist-info/WHEEL
pybinding_dev-1.0.6.dist-info/top_level.txt
pybinding_dev-1.0.6.dist-info/METADATA
pybinding_dev-1.0.6.dist-info/licenses/license.md
tests/utils/__init__.py
tests/utils/fuzzy_equal.py
tests/utils/compare_figures.py
tests/utils/path.py
pybinding/system.py
pybinding/solver.py
pybinding/constants.py
pybinding/modifier.py
pybinding/__init__.py
pybinding/wannier.py
pybinding/model.py
pybinding/disentangle.py
pybinding/leads.py
pybinding/lattice.py
pybinding/chebyshev.py
pybinding/berry.py
pybinding/shape.py
pybinding/greens.py
pybinding/parallel.py
pybinding/repository/phosphorene.py
pybinding/repository/__init__.py
pybinding/repository/examples.py
pybinding/repository/group6_tmd.py
pybinding/repository/graphene/constants.py
pybinding/repository/graphene/__init__.py
pybinding/repository/graphene/utils.py
pybinding/repository/graphene/lattice.py
pybinding/repository/graphene/shape.py
pybinding/repository/graphene/modifiers.py
pybinding/tests/test_model.py
pybinding/tests/conftest.py
pybinding/tests/test_leads.py
pybinding/tests/test_results.py
pybinding/tests/test_shape.py
pybinding/tests/test_pickle.py
pybinding/tests/test_wrapper.py
pybinding/tests/__init__.py
pybinding/tests/test_kwant.py
pybinding/tests/test_modifiers.py
pybinding/tests/test_lattice.py
pybinding/tests/test_parallel.py
pybinding/tests/test_system.py
pybinding/tests/test_kpm.py
pybinding/tests/test_solver.py
pybinding/tests/local.cfg
pybinding/tests/utils/__init__.py
pybinding/tests/utils/fuzzy_equal.py
pybinding/tests/utils/compare_figures.py
pybinding/tests/utils/path.py
pybinding/tests/baseline_data/parallel/sweep.pbz
pybinding/tests/baseline_data/parallel/ndsweep.pbz
pybinding/tests/baseline_data/shape/polygon_expected[triangle90].pbz
pybinding/tests/baseline_data/shape/polygon_expected[diamond].pbz
pybinding/tests/baseline_data/shape/polygon_expected[triangle].pbz
pybinding/tests/baseline_data/shape/polygon_expected[pentagon].pbz
pybinding/tests/baseline_data/shape/freeform.pbz
