Metadata-Version: 2.4
Name: pybinding-dev
Version: 1.0.6
Summary: Package for tight-binding calculations, Documentation: http://pybinding.site/ (c) 2015-2025
Author-email: Dean Moldovan <dean0x7d@gmail.com>
Maintainer-email: Bert Jorissen <info@bertjorissen.be>
License-Expression: BSD-3-Clause
Project-URL: repository, https://github.com/BertJorissen/pybinding
Project-URL: documentation, https://bertjorissen.github.io/pybinding/
Project-URL: changelog, https://github.com/BertJorissen/pybinding/blob/master/changelog.md
Keywords: pybinding,tight-binding,solid-state physics,physics,cmt,quantum,graphene,TMD,KPM,CPGF
Classifier: Development Status :: 5 - Production/Stable
Classifier: Intended Audience :: Science/Research
Classifier: Topic :: Scientific/Engineering :: Physics
Classifier: Programming Language :: C++
Classifier: Programming Language :: Python :: 3 :: Only
Classifier: Programming Language :: Python :: 3.10
Classifier: Programming Language :: Python :: 3.11
Classifier: Programming Language :: Python :: 3.12
Classifier: Programming Language :: Python :: 3.13
Classifier: Programming Language :: Python :: Implementation :: CPython
Requires-Python: >=3.10
License-File: license.md
Requires-Dist: numpy>=1.12
Requires-Dist: scipy>=0.19
Requires-Dist: matplotlib>=3.10.0
Requires-Dist: pytest>=5.0
Dynamic: license-file
